tiny_anthropic/__init__.py
tiny_anthropic/llm.py
tiny_anthropic/register.py
tiny_anthropic/utils.py
tinygent_anthropic-0.1.1007.dist-info/METADATA
tinygent_anthropic-0.1.1007.dist-info/WHEEL
tinygent_anthropic-0.1.1007.dist-info/entry_points.txt
tinygent_anthropic-0.1.1007.dist-info/RECORD
