Metadata-Version: 2.4
Name: tinygent-anthropic
Version: 0.1.1007
Requires-Dist: anthropic>=0.75.0
Requires-Dist: tinygent
